django_unified_response/__init__.py
django_unified_response/exceptions.py
django_unified_response/formatters.py
django_unified_response/handlers.py
django_unified_response/renderers.py
django_unified_response-0.1.0.dist-info/METADATA
django_unified_response-0.1.0.dist-info/WHEEL
django_unified_response-0.1.0.dist-info/licenses/LICENSE
django_unified_response-0.1.0.dist-info/RECORD
