Metadata-Version: 2.4
Name: django-unified-response
Version: 0.1.0
Summary: A Django library for standardized API responses.
Project-URL: Homepage, https://github.com/amirhh-2000/django-unified-response
Project-URL: Bug Tracker, https://github.com/amirhh-2000/django-unified-response/issues
Author-email: Amir Hossein <amirse7997@gmail.com>
License-File: LICENSE
Classifier: Framework :: Django
Classifier: Intended Audience :: Developers
Classifier: License :: OSI Approved :: MIT License
Classifier: Operating System :: OS Independent
Classifier: Programming Language :: Python :: 3
Requires-Python: >=3.8
Requires-Dist: django>=3.2
Requires-Dist: djangorestframework>=3.12
